gitchecker/__init__.py
gitchecker/gitchecker.py
gitchecker-2.0.0.dist-info/METADATA
gitchecker-2.0.0.dist-info/RECORD
gitchecker-2.0.0.dist-info/WHEEL
gitchecker-2.0.0.dist-info/top_level.txt
