Metadata-Version: 2.1
Name: gitchecker
Version: 2.0.0
Summary: Python GIT tool to check pending changes and get last commit info
Home-page: http://github.com/Crul/gitchecker
Author: crul
Author-email: rauljavier.vila@gmail.com
License: UNKNOWN
Platform: UNKNOWN
Classifier: Programming Language :: Python :: 3
Classifier: License :: OSI Approved :: MIT License
Classifier: Operating System :: OS Independent
Classifier: Development Status :: 5 - Production/Stable
Classifier: Intended Audience :: Developers
Classifier: Topic :: Software Development :: Version Control :: Git
Requires-Dist: gitpython
